{"ticker": "IRDM", "company": "IRIDIUM COMMUNICATIONS INC", "weight_sum": 5.19, "etfs": ["ARKQ", "ARKX"], "is_private": false, "query": "($IRDM OR \"Iridium Communications\") -is:retweet min_faves:10 since_time:1777689223 until_time:1777701993", "n_fetched": 1, "n_kept": 1, "n_dropped": 0, "kept": [{"type": "tweet", "id": "2050404477778239885", "url": "https://x.com/stocktalkweekly/status/2050404477778239885", "twitterUrl": "https://twitter.com/stocktalkweekly/status/2050404477778239885", "text": "@TedHZhang Held $IRDM thru a double from $19 entry. Still long. That weekly chart is outta a movie", "source": "Twitter for iPhone", "retweetCount": 1, "replyCount": 0, "likeCount": 12, "quoteCount": 0, "viewCount": 1684, "createdAt": "Sat May 02 02:38:16 +0000 2026", "lang": "en", "bookmarkCount": 6, "isReply": true, "inReplyToId": "2050241878683971586", "conversationId": "2050241878683971586", "displayTextRange": [11, 98], "inReplyToUserId": "776162618792869888", "inReplyToUsername": "TedHZhang", "author": {"type": "user", "userName": "stocktalkweekly", "url": "https://x.com/stocktalkweekly", "twitterUrl": "https://twitter.com/stocktalkweekly", "id": "1289823541098143744", "name": "Stock Talk", "isVerified": false, "isBlueVerified": true, "verifiedType": "Business", "profilePicture": "https://pbs.twimg.com/profile_images/1653312890756055040/zgNUIMtZ_normal.jpg", "coverPicture": "https://pbs.twimg.com/profile_banners/1289823541098143744/1683256625", "description": "", "location": "Dallas, TX", "followers": 382751, "following": 902, "status": "", "canDm": true, "canMediaTag": false, "createdAt": "Sun Aug 02 07:21:27 +0000 2020", "entities": {"description": {"urls": []}, "url": {}}, "fastFollowersCount": 0, "favouritesCount": 39158, "hasCustomTimelines": true, "isTranslator": false, "mediaCount": 6282, "statusesCount": 54206, "withheldInCountries": [], "affiliatesHighlightedLabel": {}, "possiblySensitive": false, "pinnedTweetIds": ["2006451321080258979"], "profile_bio": {"description": "AHEAD OF THE HERD \u2122 | See our full portfolio and all live entries/exits at https://t.co/nPDCUmGbv2", "entities": {"description": {"urls": [{"display_url": "whop.com/stocktalk", "expanded_url": "http://whop.com/stocktalk", "indices": [75, 98], "url": "https://t.co/nPDCUmGbv2"}]}, "url": {"urls": [{"display_url": "whop.com/stocktalk/stoc\u2026", "expanded_url": "http://www.whop.com/stocktalk/stocktalk", "indices": [0, 23], "url": "https://t.co/kwXDj0W9eo"}]}}}, "isAutomated": false, "automatedBy": null}, "extendedEntities": {}, "card": null, "place": {}, "entities": {"hashtags": [], "symbols": [{"indices": [16, 21], "text": "IRDM"}], "timestamps": [], "urls": [], "user_mentions": [{"id_str": "776162618792869888", "indices": [0, 10], "name": "Ted Zhang", "screen_name": "TedHZhang"}]}, "quoted_tweet": null, "retweeted_tweet": null, "isLimitedReply": false, "communityInfo": null, "article": null}], "dropped": [], "last_window": {"since_time": 1777689223, "until_time": 1777701993, "n_new_kept": 1, "n_new_dropped": 0}}