{"ticker": "COIN", "company": "Coinbase Global, Inc.", "weight_sum": 14.590000000000002, "etfs": ["ARKUX", "ARKK", "ARKF", "ARKW", "ARKSX", "ARKVX"], "is_private": false, "query": "($COIN OR \"Coinbase Global\") -is:retweet min_faves:10 since_time:1777840827 until_time:1777848027", "n_fetched": 13, "n_kept": 5, "n_dropped": 8, "kept": [{"type": "tweet", "id": "2050772337616634052", "url": "https://x.com/COINAppRankBot/status/2050772337616634052", "twitterUrl": "https://twitter.com/COINAppRankBot/status/2050772337616634052", "text": "\ud83d\udcb5 $COIN App Rank\n\ud83d\udcc5 2 May 8PM\n\n\ud83c\udf10 All Apps\n\u27a1\ufe0f 500\n\ud83d\udd04 500 (2 May 8AM)\n\n\ud83c\udfe6 Finance Apps\n\u27a1\ufe0f 50\n\ud83d\udd04 50 (2 May 8AM)", "source": "Twitter for iPhone", "retweetCount": 1, "replyCount": 1, "likeCount": 20, "quoteCount": 0, "viewCount": 1930, "createdAt": "Sun May 03 03:00:01 +0000 2026", "lang": "en", "bookmarkCount": 0, "isReply": false, "inReplyToId": null, "conversationId": "2050772337616634052", "displayTextRange": [0, 104], "inReplyToUserId": null, "inReplyToUsername": null, "author": {"type": "user", "userName": "COINAppRankBot", "url": "https://x.com/COINAppRankBot", "twitterUrl": "https://twitter.com/COINAppRankBot", "id": "1745646937737437185", "name": "Coinbase App Rank Bot (unofficial)", "isVerified": false, "isBlueVerified": false, "verifiedType": null, "profilePicture": "https://pbs.twimg.com/profile_images/1747129870663241728/IN5DAjGP_normal.jpg", "coverPicture": "", "description": "", "location": "", "followers": 68570, "following": 2, "status": "", "canDm": false, "canMediaTag": true, "createdAt": "Fri Jan 12 03:20:53 +0000 2024", "entities": {"description": {"urls": []}, "url": {}}, "fastFollowersCount": 0, "favouritesCount": 0, "hasCustomTimelines": true, "isTranslator": false, "mediaCount": 0, "statusesCount": 1657, "withheldInCountries": [], "affiliatesHighlightedLabel": {}, "possiblySensitive": false, "pinnedTweetIds": [], "profile_bio": {"description": "NOT ASSOCIATED WITH COINBASE\n\nApp Rank posted twice at day at 8am/8pm PST\n\nCharts/Rank Data - https://t.co/2aEPKNdIcm", "entities": {"description": {"urls": [{"display_url": "t.me/CoinbaseAppRan\u2026", "expanded_url": "https://t.me/CoinbaseAppRankBot", "indices": [94, 117], "url": "https://t.co/2aEPKNdIcm"}]}}}, "isAutomated": false, "automatedBy": null}, "extendedEntities": {}, "card": null, "place": {}, "entities": {"hashtags": [], "symbols": [{"indices": [2, 7], "text": "COIN"}], "timestamps": [], "urls": [], "user_mentions": []}, "quoted_tweet": null, "retweeted_tweet": null, "isLimitedReply": false, "communityInfo": null, "article": null}, {"type": "tweet", "id": "2050879542282035306", "url": "https://x.com/scottmelker/status/2050879542282035306", "twitterUrl": "https://twitter.com/scottmelker/status/2050879542282035306", "text": "COINBASE $COIN ACTIVATES TAS TRADING FOR $XRP FUTURES", "source": "Twitter for iPhone", "retweetCount": 5, "replyCount": 10, "likeCount": 56, "quoteCount": 0, "viewCount": 4076, "createdAt": "Sun May 03 10:06:01 +0000 2026", "lang": "en", "bookmarkCount": 0, "isReply": false, "inReplyToId": null, "conversationId": "2050879542282035306", "displayTextRange": [0, 53], "inReplyToUserId": null, "inReplyToUsername": null, "author": {"type": "user", "userName": "scottmelker", "url": "https://x.com/scottmelker", "twitterUrl": "https://twitter.com/scottmelker", "id": "17351167", "name": "The Wolf Of All Streets", "isVerified": false, "isBlueVerified": true, "verifiedType": null, "profilePicture": "https://pbs.twimg.com/profile_images/1927915527990833152/cGrIp3T0_normal.jpg", "coverPicture": "https://pbs.twimg.com/profile_banners/17351167/1777149874", "description": "", "location": "Not Financial Advice", "followers": 1086949, "following": 1217, "status": "", "canDm": true, "canMediaTag": true, "createdAt": "Wed Nov 12 22:58:17 +0000 2008", "entities": {"description": {"urls": []}, "url": {}}, "fastFollowersCount": 0, "favouritesCount": 95826, "hasCustomTimelines": true, "isTranslator": false, "mediaCount": 15398, "statusesCount": 141491, "withheldInCountries": [], "affiliatesHighlightedLabel": {}, "possiblySensitive": false, "pinnedTweetIds": ["2036540222368833742"], "profile_bio": {"description": "The Wolf Of All Streets | The Daily Wolf | Media Host | Author | Markets | Hot Takes | Bitcoin | WOAS NETWORK I Married up to @emimelker", "entities": {"description": {"user_mentions": [{"id_str": "", "indices": [126, 136], "name": "", "screen_name": "emimelker"}]}, "url": {"urls": [{"display_url": "linktr.ee/scottmelker", "expanded_url": "https://linktr.ee/scottmelker", "indices": [0, 23], "url": "https://t.co/KLPVEcsVKP"}]}}}, "isAutomated": false, "automatedBy": null}, "extendedEntities": {}, "card": null, "place": {}, "entities": {"hashtags": [], "symbols": [{"indices": [9, 14], "text": "COIN"}, {"indices": [41, 45], "text": "XRP"}], "timestamps": [], "urls": [], "user_mentions": []}, "quoted_tweet": null, "retweeted_tweet": null, "isLimitedReply": false, "communityInfo": null, "article": null}, {"type": "tweet", "id": "2050960873473122324", "url": "https://x.com/chad_ventures/status/2050960873473122324", "twitterUrl": "https://twitter.com/chad_ventures/status/2050960873473122324", "text": "$COIN is still stuck underneath the strong $210-$200 resistance zone, which needs to be breached to confirm a bottom\n\nOverall structure looking solid, though. Clean double bottom at the 0.618 log Fib, which nobody believed would hold. https://t.co/4rpFCXnLYz", "source": "Twitter for iPhone", "retweetCount": 2, "replyCount": 4, "likeCount": 32, "quoteCount": 0, "viewCount": 1207, "createdAt": "Sun May 03 15:29:11 +0000 2026", "lang": "en", "bookmarkCount": 2, "isReply": false, "inReplyToId": null, "conversationId": "2050960873473122324", "displayTextRange": [0, 234], "inReplyToUserId": null, "inReplyToUsername": null, "author": {"type": "user", "userName": "chad_ventures", "url": "https://x.com/chad_ventures", "twitterUrl": "https://twitter.com/chad_ventures", "id": "1058069565635215360", "name": "chad.", "isVerified": false, "isBlueVerified": true, "verifiedType": null, "profilePicture": "https://pbs.twimg.com/profile_images/2006930329882316800/Zd1EJkJz_normal.jpg", "coverPicture": "https://pbs.twimg.com/profile_banners/1058069565635215360/1767322718", "description": "", "location": "Not Financial Advice", "followers": 19337, "following": 164, "status": "", "canDm": true, "canMediaTag": false, "createdAt": "Thu Nov 01 18:53:37 +0000 2018", "entities": {"description": {"urls": []}, "url": {}}, "fastFollowersCount": 0, "favouritesCount": 37381, "hasCustomTimelines": true, "isTranslator": false, "mediaCount": 7196, "statusesCount": 21161, "withheldInCountries": [], "affiliatesHighlightedLabel": {}, "possiblySensitive": false, "pinnedTweetIds": ["2049185628298858797"], "profile_bio": {"description": "Market Analyst Focused on Technical Analysis and Commentary on Indices, Stocks, Crypto, and More.", "entities": {"description": {}, "url": {"urls": [{"display_url": "youtube.com/@chad_ventures", "expanded_url": "https://www.youtube.com/@chad_ventures", "indices": [0, 23], "url": "https://t.co/Lf3EmQVGPP"}]}}}, "isAutomated": false, "automatedBy": null}, "extendedEntities": {"media": [{"allow_download_status": {"allow_download": true}, "display_url": "pic.twitter.com/4rpFCXnLYz", "expanded_url": "https://twitter.com/chad_ventures/status/2050960873473122324/photo/1", "ext_media_availability": {"status": "Available"}, "features": {"large": {"faces": []}, "orig": {"faces": []}}, "id_str": "2050960865281650688", "indices": [235, 258], "media_key": "3_2050960865281650688", "media_results": {"id": "QXBpTWVkaWFSZXN1bHRzOgwAAQoAARx2egpfVzAACgACHHZ6DEeXIBQAAA==", "result": {"__typename": "ApiMedia", "id": "QXBpTWVkaWE6DAABCgABHHZ6Cl9XMAAKAAIcdnoMR5cgFAAA", "media_key": "3_2050960865281650688"}}, "media_url_https": "https://pbs.twimg.com/media/HHZ6Cl9XMAAvmO9.jpg", "original_info": {"focus_rects": [{"h": 1598, "w": 2854, "x": 0, "y": 0}, {"h": 1736, "w": 1736, "x": 200, "y": 0}, {"h": 1736, "w": 1523, "x": 307, "y": 0}, {"h": 1736, "w": 868, "x": 634, "y": 0}, {"h": 1736, "w": 2854, "x": 0, "y": 0}], "height": 1736, "width": 2854}, "sizes": {"large": {"h": 1246, "w": 2048}}, "type": "photo", "url": "https://t.co/4rpFCXnLYz"}]}, "card": null, "place": {}, "entities": {"hashtags": [], "symbols": [{"indices": [0, 5], "text": "COIN"}], "timestamps": [], "urls": [], "user_mentions": []}, "quoted_tweet": null, "retweeted_tweet": null, "isLimitedReply": false, "communityInfo": null, "article": null}, {"type": "tweet", "id": "2050953534124761091", "url": "https://x.com/COINAppRankBot/status/2050953534124761091", "twitterUrl": "https://twitter.com/COINAppRankBot/status/2050953534124761091", "text": "\ud83d\udcb5 $COIN App Rank\n\ud83d\udcc5 3 May 8AM\n\n\ud83c\udf10 All Apps\n\u27a1\ufe0f 500\n\ud83d\udd04 500 (2 May 8PM)\n\n\ud83c\udfe6 Finance Apps\n\u27a1\ufe0f 50\n\ud83d\udd04 50 (2 May 8PM)", "source": "Twitter for iPhone", "retweetCount": 0, "replyCount": 1, "likeCount": 10, "quoteCount": 0, "viewCount": 1768, "createdAt": "Sun May 03 15:00:02 +0000 2026", "lang": "en", "bookmarkCount": 1, "isReply": false, "inReplyToId": null, "conversationId": "2050953534124761091", "displayTextRange": [0, 104], "inReplyToUserId": null, "inReplyToUsername": null, "author": {"type": "user", "userName": "COINAppRankBot", "url": "https://x.com/COINAppRankBot", "twitterUrl": "https://twitter.com/COINAppRankBot", "id": "1745646937737437185", "name": "Coinbase App Rank Bot (unofficial)", "isVerified": false, "isBlueVerified": false, "verifiedType": null, "profilePicture": "https://pbs.twimg.com/profile_images/1747129870663241728/IN5DAjGP_normal.jpg", "coverPicture": "", "description": "", "location": "", "followers": 68558, "following": 2, "status": "", "canDm": false, "canMediaTag": true, "createdAt": "Fri Jan 12 03:20:53 +0000 2024", "entities": {"description": {"urls": []}, "url": {}}, "fastFollowersCount": 0, "favouritesCount": 0, "hasCustomTimelines": true, "isTranslator": false, "mediaCount": 0, "statusesCount": 1658, "withheldInCountries": [], "affiliatesHighlightedLabel": {}, "possiblySensitive": false, "pinnedTweetIds": [], "profile_bio": {"description": "NOT ASSOCIATED WITH COINBASE\n\nApp Rank posted twice at day at 8am/8pm PST\n\nCharts/Rank Data - https://t.co/2aEPKNdIcm", "entities": {"description": {"urls": [{"display_url": "t.me/CoinbaseAppRan\u2026", "expanded_url": "https://t.me/CoinbaseAppRankBot", "indices": [94, 117], "url": "https://t.co/2aEPKNdIcm"}]}}}, "isAutomated": false, "automatedBy": null}, "extendedEntities": {}, "card": null, "place": {}, "entities": {"hashtags": [], "symbols": [{"indices": [2, 7], "text": "COIN"}], "timestamps": [], "urls": [], "user_mentions": []}, "quoted_tweet": null, "retweeted_tweet": null, "isLimitedReply": false, "communityInfo": null, "article": null}, {"type": "tweet", "id": "2050987199340884087", "url": "https://x.com/Zac_Markovich/status/2050987199340884087", "twitterUrl": "https://twitter.com/Zac_Markovich/status/2050987199340884087", "text": "$COIN Target upper AVWAP. https://t.co/sLglQV5aD0", "source": "Twitter for iPhone", "retweetCount": 0, "replyCount": 4, "likeCount": 11, "quoteCount": 0, "viewCount": 1201, "createdAt": "Sun May 03 17:13:48 +0000 2026", "lang": "ht", "bookmarkCount": 1, "isReply": false, "inReplyToId": null, "conversationId": "2050987199340884087", "displayTextRange": [0, 25], "inReplyToUserId": null, "inReplyToUsername": null, "author": {"type": "user", "userName": "Zac_Markovich", "url": "https://x.com/Zac_Markovich", "twitterUrl": "https://twitter.com/Zac_Markovich", "id": "1939779878896676867", "name": "Zachary Markovich", "isVerified": false, "isBlueVerified": true, "verifiedType": null, "profilePicture": "https://pbs.twimg.com/profile_images/1994859540207054848/h9dB4P2y_normal.jpg", "coverPicture": "https://pbs.twimg.com/profile_banners/1939779878896676867/1764476513", "description": "", "location": "Denver, CO", "followers": 22927, "following": 291, "status": "", "canDm": false, "canMediaTag": true, "createdAt": "Mon Jun 30 20:15:57 +0000 2025", "entities": {"description": {"urls": []}, "url": {}}, "fastFollowersCount": 0, "favouritesCount": 14547, "hasCustomTimelines": true, "isTranslator": false, "mediaCount": 5592, "statusesCount": 14591, "withheldInCountries": [], "affiliatesHighlightedLabel": {}, "possiblySensitive": false, "pinnedTweetIds": ["2045270272551399643"], "profile_bio": {"description": "Trader since 2014 | CMT | X Subscription out now\u2192 ($1) Technical analysis on Stocks & Crypto. Not financial advice.", "entities": {"description": {}, "url": {"urls": [{"display_url": "youtube.com/@Zac_Markovich", "expanded_url": "https://www.youtube.com/@Zac_Markovich", "indices": [0, 23], "url": "https://t.co/mf7K34sfql"}]}}}, "isAutomated": false, "automatedBy": null}, "extendedEntities": {"media": [{"allow_download_status": {"allow_download": true}, "display_url": "pic.twitter.com/sLglQV5aD0", "expanded_url": "https://twitter.com/Zac_Markovich/status/2050987199340884087/photo/1", "ext_media_availability": {"status": "Available"}, "features": {"large": {"faces": []}, "orig": {"faces": []}}, "id_str": "2050987154365378562", "indices": [26, 49], "media_key": "3_2050987154365378562", "media_results": {"id": "QXBpTWVkaWFSZXN1bHRzOgwAAQoAARx2kfNG1nACCgACHHaR/b+WMHcAAA==", "result": {"__typename": "ApiMedia", "id": "QXBpTWVkaWE6DAABCgABHHaR80bWcAIKAAIcdpH9v5YwdwAA", "media_key": "3_2050987154365378562"}}, "media_url_https": "https://pbs.twimg.com/media/HHaR80bWcAI8gRQ.jpg", "original_info": {"focus_rects": [{"h": 1110, "w": 1982, "x": 0, "y": 0}, {"h": 1234, "w": 1234, "x": 0, "y": 0}, {"h": 1234, "w": 1082, "x": 0, "y": 0}, {"h": 1234, "w": 617, "x": 137, "y": 0}, {"h": 1234, "w": 1982, "x": 0, "y": 0}], "height": 1234, "width": 1982}, "sizes": {"large": {"h": 1234, "w": 1982}}, "type": "photo", "url": "https://t.co/sLglQV5aD0"}]}, "card": null, "place": {}, "entities": {"hashtags": [], "symbols": [{"indices": [0, 5], "text": "COIN"}], "timestamps": [], "urls": [], "user_mentions": []}, "quoted_tweet": null, "retweeted_tweet": null, "isLimitedReply": false, "communityInfo": null, "article": null}], "dropped": [{"reason": "cashtags=10", "tweet": {"type": "tweet", "id": "2050874759450087911", "url": "https://x.com/JesseCohenInv/status/2050874759450087911", "twitterUrl": "https://twitter.com/JesseCohenInv/status/2050874759450087911", "text": "Happy Sunday!\n\nHere Are My #Top5ThingsToKnowThisWeek:\n\n1. U.S. Jobs Report\n2. ISM PMI Surveys\n3. $AMD $PLTR $IREN $LITE Earnings\n4. $DIS $UBER $PYPL $COIN Earnings\n5. $NVO $PFE Earnings\n\nMay The Trading Gods Be With You \ud83d\ude4f https://t.co/eM7NTsAdLN", "source": "Twitter for iPhone", "retweetCount": 5, "replyCount": 18, "likeCount": 27, "quoteCount": 1, "viewCount": 9461, "createdAt": "Sun May 03 09:47:00 +0000 2026", "lang": "en", "bookmarkCount": 7, "isReply": false, "inReplyToId": null, "conversationId": "2050874759450087911", "displayTextRange": [0, 221], "inReplyToUserId": null, "inReplyToUsername": null, "author": {"type": "user", "userName": "JesseCohenInv", "url": "https://x.com/JesseCohenInv", "twitterUrl": "https://twitter.com/JesseCohenInv", "id": "19534637", "name": "Jesse Cohen", "isVerified": false, "isBlueVerified": true, "verifiedType": null, "profilePicture": "https://pbs.twimg.com/profile_images/966634456911155201/vsMQLdlR_normal.jpg", "coverPicture": "https://pbs.twimg.com/profile_banners/19534637/1519298295", "description": "", "location": "Tel Aviv", "followers": 179995, "following": 906, "status": "", "canDm": true, "canMediaTag": false, "createdAt": "Mon Jan 26 13:52:39 +0000 2009", "entities": {"description": {"urls": []}, "url": {}}, "fastFollowersCount": 0, "favouritesCount": 9447, "hasCustomTimelines": true, "isTranslator": false, "mediaCount": 17632, "statusesCount": 89243, "withheldInCountries": [], "affiliatesHighlightedLabel": {}, "possiblySensitive": false, "pinnedTweetIds": ["2050555969868870032"], "profile_bio": {"description": "Global Markets Analyst @Investingcom + I run the https://t.co/6oJBJzhu57 Twitter account.\n\nBorn and raised in New Jersey. Currently in Tel Aviv.", "entities": {"description": {"urls": [{"display_url": "Investing.com", "expanded_url": "http://Investing.com", "indices": [49, 72], "url": "https://t.co/6oJBJzhu57"}], "user_mentions": [{"id_str": "", "indices": [23, 36], "name": "", "screen_name": "Investingcom"}]}, "url": {"urls": [{"display_url": "investing.com/members/202100\u2026", "expanded_url": "https://www.investing.com/members/202100653", "indices": [0, 23], "url": "https://t.co/Jnv93JIBBE"}]}}}, "isAutomated": false, "automatedBy": null}, "extendedEntities": {"media": [{"allow_download_status": {"allow_download": true}, "display_url": "pic.twitter.com/eM7NTsAdLN", "expanded_url": "https://twitter.com/JesseCohenInv/status/2050874759450087911/photo/1", "ext_media_availability": {"status": "Available"}, "features": {"large": {"faces": [{"h": 233, "w": 233, "x": 739, "y": 291}, {"h": 253, "w": 253, "x": 557, "y": 145}, {"h": 303, "w": 303, "x": 1037, "y": 155}, {"h": 291, "w": 291, "x": 329, "y": 193}]}, "orig": {"faces": [{"h": 240, "w": 240, "x": 762, "y": 300}, {"h": 261, "w": 261, "x": 574, "y": 150}, {"h": 313, "w": 313, "x": 1068, "y": 160}, {"h": 300, "w": 300, "x": 339, "y": 199}]}}, "id_str": "2050874554382495744", "indices": [222, 245], "media_key": "3_2050874554382495744", "media_results": {"id": "QXBpTWVkaWFSZXN1bHRzOgwAAQoAARx2K4qM2zAACgACHHYrukvWUecAAA==", "result": {"__typename": "ApiMedia", "id": "QXBpTWVkaWE6DAABCgABHHYriozbMAAKAAIcdiu6S9ZR5wAA", "media_key": "3_2050874554382495744"}}, "media_url_https": "https://pbs.twimg.com/media/HHYriozbMAA0MRS.jpg", "original_info": {"focus_rects": [{"h": 1181, "w": 2109, "x": 0, "y": 402}, {"h": 1583, "w": 1583, "x": 0, "y": 0}, {"h": 1583, "w": 1389, "x": 0, "y": 0}, {"h": 1583, "w": 792, "x": 0, "y": 0}, {"h": 1583, "w": 2109, "x": 0, "y": 0}], "height": 1583, "width": 2109}, "sizes": {"large": {"h": 1537, "w": 2048}}, "type": "photo", "url": "https://t.co/eM7NTsAdLN"}, {"allow_download_status": {"allow_download": true}, "display_url": "pic.twitter.com/eM7NTsAdLN", "expanded_url": "https://twitter.com/JesseCohenInv/status/2050874759450087911/photo/1", "ext_media_availability": {"status": "Available"}, "features": {"large": {"faces": [{"h": 447, "w": 447, "x": 391, "y": 623}]}, "orig": {"faces": [{"h": 461, "w": 461, "x": 403, "y": 642}]}}, "id_str": "2050874613236899840", "indices": [222, 245], "media_key": "3_2050874613236899840", "media_results": {"id": "QXBpTWVkaWFSZXN1bHRzOgwAAQoAARx2K5hA2iAACgACHHYrukvWUecAAA==", "result": {"__typename": "ApiMedia", "id": "QXBpTWVkaWE6DAABCgABHHYrmEDaIAAKAAIcdiu6S9ZR5wAA", "media_key": "3_2050874613236899840"}}, "media_url_https": "https://pbs.twimg.com/media/HHYrmEDaIAA0zYe.jpg", "original_info": {"focus_rects": [{"h": 1181, "w": 2109, "x": 0, "y": 402}, {"h": 1583, "w": 1583, "x": 0, "y": 0}, {"h": 1583, "w": 1389, "x": 0, "y": 0}, {"h": 1583, "w": 792, "x": 0, "y": 0}, {"h": 1583, "w": 2109, "x": 0, "y": 0}], "height": 1583, "width": 2109}, "sizes": {"large": {"h": 1537, "w": 2048}}, "type": "photo", "url": "https://t.co/eM7NTsAdLN"}, {"allow_download_status": {"allow_download": true}, "display_url": "pic.twitter.com/eM7NTsAdLN", "expanded_url": "https://twitter.com/JesseCohenInv/status/2050874759450087911/photo/1", "ext_media_availability": {"status": "Available"}, "features": {"large": {"faces": [{"h": 471, "w": 471, "x": 1087, "y": 271}, {"h": 369, "w": 369, "x": 827, "y": 795}]}, "orig": {"faces": [{"h": 486, "w": 486, "x": 1120, "y": 280}, {"h": 381, "w": 381, "x": 852, "y": 819}]}}, "id_str": "2050874690022092800", "indices": [222, 245], "media_key": "3_2050874690022092800", "media_results": {"id": "QXBpTWVkaWFSZXN1bHRzOgwAAQoAARx2K6ohmzAACgACHHYrukvWUecAAA==", "result": {"__typename": "ApiMedia", "id": "QXBpTWVkaWE6DAABCgABHHYrqiGbMAAKAAIcdiu6S9ZR5wAA", "media_key": "3_2050874690022092800"}}, "media_url_https": "https://pbs.twimg.com/media/HHYrqiGbMAAkWpj.jpg", "original_info": {"focus_rects": [{"h": 1181, "w": 2109, "x": 0, "y": 402}, {"h": 1583, "w": 1583, "x": 526, "y": 0}, {"h": 1583, "w": 1389, "x": 624, "y": 0}, {"h": 1583, "w": 792, "x": 922, "y": 0}, {"h": 1583, "w": 2109, "x": 0, "y": 0}], "height": 1583, "width": 2109}, "sizes": {"large": {"h": 1537, "w": 2048}}, "type": "photo", "url": "https://t.co/eM7NTsAdLN"}, {"allow_download_status": {"allow_download": true}, "display_url": "pic.twitter.com/eM7NTsAdLN", "expanded_url": "https://twitter.com/JesseCohenInv/status/2050874759450087911/photo/1", "ext_media_availability": {"status": "Available"}, "features": {"large": {"faces": [{"h": 268, "w": 268, "x": 375, "y": 141}]}, "orig": {"faces": [{"h": 268, "w": 268, "x": 375, "y": 141}]}}, "id_str": "2050874744925478914", "indices": [222, 245], "media_key": "3_2050874744925478914", "media_results": {"id": "QXBpTWVkaWFSZXN1bHRzOgwAAQoAARx2K7bqGmACCgACHHYrukvWUecAAA==", "result": {"__typename": "ApiMedia", "id": "QXBpTWVkaWE6DAABCgABHHYrtuoaYAIKAAIcdiu6S9ZR5wAA", "media_key": "3_2050874744925478914"}}, "media_url_https": "https://pbs.twimg.com/media/HHYrtuoaYAIobMG.jpg", "original_info": {"focus_rects": [{"h": 492, "w": 879, "x": 0, "y": 168}, {"h": 660, "w": 660, "x": 0, "y": 0}, {"h": 660, "w": 579, "x": 0, "y": 0}, {"h": 660, "w": 330, "x": 0, "y": 0}, {"h": 660, "w": 879, "x": 0, "y": 0}], "height": 660, "width": 879}, "sizes": {"large": {"h": 660, "w": 879}}, "type": "photo", "url": "https://t.co/eM7NTsAdLN"}]}, "card": null, "place": {}, "entities": {"hashtags": [{"indices": [27, 52], "text": "Top5ThingsToKnowThisWeek"}], "symbols": [{"indices": [97, 101], "text": "AMD"}, {"indices": [102, 107], "text": "PLTR"}, {"indices": [108, 113], "text": "IREN"}, {"indices": [114, 119], "text": "LITE"}, {"indices": [132, 136], "text": "DIS"}, {"indices": [137, 142], "text": "UBER"}, {"indices": [143, 148], "text": "PYPL"}, {"indices": [149, 154], "text": "COIN"}, {"indices": [167, 171], "text": "NVO"}, {"indices": [172, 176], "text": "PFE"}], "timestamps": [], "urls": [], "user_mentions": []}, "quoted_tweet": {"type": "tweet", "id": "2050620609839657015", "url": "https://x.com/JesseCohenInv/status/2050620609839657015", "twitterUrl": "https://twitter.com/JesseCohenInv/status/2050620609839657015", "text": "\u26a0\ufe0fBIG EARNINGS WEEK AHEAD \ud83d\udc40\ud83d\udc40\n\n\u2022 Monday: $PLTR\n\u2022 Tuesday: $AMD $SHOP $MSTR $PYPL\n\u2022 Wednesday: $DIS $UBER $NVO $ARM $APP\n\u2022 Thursday: $IREN $CRWV $AAOI $COIN $MCD\n\u2022 Friday: $WEN\n\n$SPY $QQQ https://t.co/6w63Q2qvJ8", "source": "Twitter for iPhone", "retweetCount": 90, "replyCount": 27, "likeCount": 394, "quoteCount": 10, "viewCount": 47271, "createdAt": "Sat May 02 16:57:06 +0000 2026", "lang": "en", "bookmarkCount": 117, "isReply": false, "inReplyToId": null, "conversationId": "2050620609839657015", "displayTextRange": [0, 185], "inReplyToUserId": null, "inReplyToUsername": null, "author": {"type": "user", "userName": "JesseCohenInv", "url": "https://x.com/JesseCohenInv", "twitterUrl": "https://twitter.com/JesseCohenInv", "id": "19534637", "name": "Jesse Cohen", "isVerified": false, "isBlueVerified": true, "verifiedType": null, "profilePicture": "https://pbs.twimg.com/profile_images/966634456911155201/vsMQLdlR_normal.jpg", "coverPicture": "https://pbs.twimg.com/profile_banners/19534637/1519298295", "description": "", "location": "Tel Aviv", "followers": 179995, "following": 906, "status": "", "canDm": true, "canMediaTag": false, "createdAt": "Mon Jan 26 13:52:39 +0000 2009", "entities": {"description": {"urls": []}, "url": {}}, "fastFollowersCount": 0, "favouritesCount": 9447, "hasCustomTimelines": true, "isTranslator": false, "mediaCount": 17632, "statusesCount": 89243, "withheldInCountries": [], "affiliatesHighlightedLabel": {}, "possiblySensitive": false, "pinnedTweetIds": ["2050555969868870032"], "profile_bio": {"description": "Global Markets Analyst @Investingcom + I run the https://t.co/6oJBJzhu57 Twitter account.\n\nBorn and raised in New Jersey. Currently in Tel Aviv.", "entities": {"description": {"urls": [{"display_url": "Investing.com", "expanded_url": "http://Investing.com", "indices": [49, 72], "url": "https://t.co/6oJBJzhu57"}], "user_mentions": [{"id_str": "", "indices": [23, 36], "name": "", "screen_name": "Investingcom"}]}, "url": {"urls": [{"display_url": "investing.com/members/202100\u2026", "expanded_url": "https://www.investing.com/members/202100653", "indices": [0, 23], "url": "https://t.co/Jnv93JIBBE"}]}}}, "isAutomated": false, "automatedBy": null}, "extendedEntities": {"media": [{"allow_download_status": {"allow_download": true}, "display_url": "pic.twitter.com/6w63Q2qvJ8", "expanded_url": "https://twitter.com/JesseCohenInv/status/2050620609839657015/photo/1", "ext_media_availability": {"status": "Available"}, "features": {"large": {"faces": [{"h": 205, "w": 205, "x": 1147, "y": 817}, {"h": 181, "w": 181, "x": 1385, "y": 283}, {"h": 269, "w": 269, "x": 435, "y": 703}]}, "orig": {"faces": [{"h": 295, "w": 295, "x": 1648, "y": 1174}, {"h": 261, "w": 261, "x": 1989, "y": 407}, {"h": 387, "w": 387, "x": 625, "y": 1010}]}}, "id_str": "2050620305714913281", "indices": [186, 209], "media_key": "3_2050620305714913281", "media_results": {"id": "QXBpTWVkaWFSZXN1bHRzOgwAAQoAARx1RE2rVyABCgACHHVElHqWcDcAAA==", "result": {"__typename": "ApiMedia", "id": "QXBpTWVkaWE6DAABCgABHHVETatXIAEKAAIcdUSUepZwNwAA", "media_key": "3_2050620305714913281"}}, "media_url_https": "https://pbs.twimg.com/media/HHVETatXIAEJqhU.jpg", "original_info": {"focus_rects": [{"h": 1646, "w": 2940, "x": 0, "y": 0}, {"h": 1647, "w": 1647, "x": 1293, "y": 0}, {"h": 1647, "w": 1445, "x": 1495, "y": 0}, {"h": 1647, "w": 824, "x": 2116, "y": 0}, {"h": 1647, "w": 2940, "x": 0, "y": 0}], "height": 1647, "width": 2940}, "sizes": {"large": {"h": 1147, "w": 2048}}, "type": "photo", "url": "https://t.co/6w63Q2qvJ8"}]}, "card": null, "place": {}, "entities": {"hashtags": [], "symbols": [{"indices": [40, 45], "text": "PLTR"}, {"indices": [57, 61], "text": "AMD"}, {"indices": [62, 67], "text": "SHOP"}, {"indices": [68, 73], "text": "MSTR"}, {"indices": [74, 79], "text": "PYPL"}, {"indices": [93, 97], "text": "DIS"}, {"indices": [98, 103], "text": "UBER"}, {"indices": [104, 108], "text": "NVO"}, {"indices": [109, 113], "text": "ARM"}, {"indices": [114, 118], "text": "APP"}, {"indices": [131, 136], "text": "IREN"}, {"indices": [137, 142], "text": "CRWV"}, {"indices": [143, 148], "text": "AAOI"}, {"indices": [149, 154], "text": "COIN"}, {"indices": [155, 159], "text": "MCD"}, {"indices": [170, 174], "text": "WEN"}, {"indices": [176, 180], "text": "SPY"}, {"indices": [181, 185], "text": "QQQ"}], "timestamps": [], "urls": [], "user_mentions": []}, "quoted_tweet": null, "retweeted_tweet": null, "isLimitedReply": false, "communityInfo": null, "article": null}, "retweeted_tweet": null, "isLimitedReply": false, "communityInfo": null, "article": null}}, {"reason": "cashtags=30", "tweet": {"type": "tweet", "id": "2050944173185110158", "url": "https://x.com/wallstengine/status/2050944173185110158", "twitterUrl": "https://twitter.com/wallstengine/status/2050944173185110158", "text": "UPCOMING KEY EARNINGS - WEEK OF MAY 3, 2026\n\nMon: $PLTR, $DUOL, $PINS, $ON, $VRTX\n\nTues: $PYPL, $SHOP, $AMD, $SMCI, $MSTR, $ANET\n\nWed: $UBER, $DIS, $ARM, $IONQ, $SNAP\n\nThurs: $MCD, $DDOG, $U, $COIN, $CRWV, $ABNB, $TTD, $NET\n\nFri: $WULF, $ENB, $BAM, $WEN, $FIS, $FLR\n\nFollow me @wallstengine for FREE, FAST, ACCURATE, & CONSISTENT stock market updates, actionable news, earnings highlights, and market commentary.", "source": "Twitter for iPhone", "retweetCount": 9, "replyCount": 7, "likeCount": 48, "quoteCount": 2, "viewCount": 4458, "createdAt": "Sun May 03 14:22:50 +0000 2026", "lang": "en", "bookmarkCount": 22, "isReply": false, "inReplyToId": null, "conversationId": "2050944173185110158", "displayTextRange": [0, 276], "inReplyToUserId": null, "inReplyToUsername": null, "author": {"type": "user", "userName": "wallstengine", "url": "https://x.com/wallstengine", "twitterUrl": "https://twitter.com/wallstengine", "id": "1508426880860704771", "name": "Wall St Engine", "isVerified": false, "isBlueVerified": true, "verifiedType": null, "profilePicture": "https://pbs.twimg.com/profile_images/1691846947857178624/oZp5wB4r_normal.jpg", "coverPicture": "https://pbs.twimg.com/profile_banners/1508426880860704771/1693301985", "description": "", "location": "Wall Street", "followers": 143286, "following": 771, "status": "", "canDm": true, "canMediaTag": true, "createdAt": "Mon Mar 28 12:53:25 +0000 2022", "entities": {"description": {"urls": []}, "url": {}}, "fastFollowersCount": 0, "favouritesCount": 43272, "hasCustomTimelines": true, "isTranslator": false, "mediaCount": 14611, "statusesCount": 46781, "withheldInCountries": [], "affiliatesHighlightedLabel": {}, "possiblySensitive": false, "pinnedTweetIds": ["2045178391087989245"], "profile_bio": {"description": "Fast, accurate, consistent stock market news, earnings highlights & more. By Brillinsight. Not financial advice.", "entities": {"description": {}, "url": {"urls": [{"display_url": "whop.com/stocktalk/stoc\u2026", "expanded_url": "https://whop.com/stocktalk/stocktalk?a=wallstengine", "indices": [0, 23], "url": "https://t.co/Br36qaiAD6"}]}}}, "isAutomated": false, "automatedBy": null}, "extendedEntities": {"media": [{"allow_download_status": {"allow_download": true}, "display_url": "pic.twitter.com/cyBGXHewjD", "expanded_url": "https://twitter.com/wallstengine/status/2050944173185110158/photo/1", "ext_media_availability": {"status": "Available"}, "features": {"large": {"faces": [{"h": 111, "w": 111, "x": 1777, "y": 577}, {"h": 141, "w": 141, "x": 943, "y": 821}, {"h": 145, "w": 145, "x": 423, "y": 1681}, {"h": 167, "w": 167, "x": 1067, "y": 651}, {"h": 149, "w": 149, "x": 543, "y": 883}, {"h": 161, "w": 161, "x": 1227, "y": 947}, {"h": 163, "w": 163, "x": 129, "y": 429}, {"h": 157, "w": 157, "x": 819, "y": 759}, {"h": 163, "w": 163, "x": 657, "y": 865}, {"h": 195, "w": 195, "x": 395, "y": 783}]}, "orig": {"faces": [{"h": 171, "w": 171, "x": 2727, "y": 886}, {"h": 217, "w": 217, "x": 1448, "y": 1261}, {"h": 223, "w": 223, "x": 650, "y": 2580}, {"h": 257, "w": 257, "x": 1638, "y": 1000}, {"h": 230, "w": 230, "x": 834, "y": 1356}, {"h": 248, "w": 248, "x": 1883, "y": 1454}, {"h": 251, "w": 251, "x": 199, "y": 659}, {"h": 242, "w": 242, "x": 1258, "y": 1165}, {"h": 251, "w": 251, "x": 1009, "y": 1328}, {"h": 300, "w": 300, "x": 607, "y": 1202}]}}, "id_str": "2050942864780402688", "indices": [277, 300], "media_key": "3_2050942864780402688", "media_results": {"id": "QXBpTWVkaWFSZXN1bHRzOgwAAQoAARx2aatN26AACgACHHZq2/DbEI4AAA==", "result": {"__typename": "ApiMedia", "id": "QXBpTWVkaWE6DAABCgABHHZpq03boAAKAAIcdmrb8NsQjgAA", "media_key": "3_2050942864780402688"}}, "media_url_https": "https://pbs.twimg.com/media/HHZpq03boAA4lHL.jpg", "original_info": {"focus_rects": [{"h": 1760, "w": 3142, "x": 0, "y": 1356}, {"h": 3116, "w": 3116, "x": 26, "y": 0}, {"h": 3116, "w": 2733, "x": 409, "y": 0}, {"h": 3116, "w": 1558, "x": 1184, "y": 0}, {"h": 3116, "w": 3142, "x": 0, "y": 0}], "height": 3116, "width": 3142}, "sizes": {"large": {"h": 2031, "w": 2048}}, "type": "photo", "url": "https://t.co/cyBGXHewjD"}]}, "card": null, "place": {}, "entities": {"hashtags": [], "symbols": [{"indices": [50, 55], "text": "PLTR"}, {"indices": [57, 62], "text": "DUOL"}, {"indices": [64, 69], "text": "PINS"}, {"indices": [71, 74], "text": "ON"}, {"indices": [76, 81], "text": "VRTX"}, {"indices": [89, 94], "text": "PYPL"}, {"indices": [96, 101], "text": "SHOP"}, {"indices": [103, 107], "text": "AMD"}, {"indices": [109, 114], "text": "SMCI"}, {"indices": [116, 121], "text": "MSTR"}, {"indices": [123, 128], "text": "ANET"}, {"indices": [135, 140], "text": "UBER"}, {"indices": [142, 146], "text": "DIS"}, {"indices": [148, 152], "text": "ARM"}, {"indices": [154, 159], "text": "IONQ"}, {"indices": [161, 166], "text": "SNAP"}, {"indices": [175, 179], "text": "MCD"}, {"indices": [181, 186], "text": "DDOG"}, {"indices": [188, 190], "text": "U"}, {"indices": [192, 197], "text": "COIN"}, {"indices": [199, 204], "text": "CRWV"}, {"indices": [206, 211], "text": "ABNB"}, {"indices": [213, 217], "text": "TTD"}, {"indices": [219, 223], "text": "NET"}, {"indices": [230, 235], "text": "WULF"}, {"indices": [237, 241], "text": "ENB"}, {"indices": [243, 247], "text": "BAM"}, {"indices": [249, 253], "text": "WEN"}, {"indices": [255, 259], "text": "FIS"}, {"indices": [261, 265], "text": "FLR"}], "urls": [], "user_mentions": [{"id_str": "1508426880860704771", "indices": [277, 290], "name": "Wall St Engine", "screen_name": "wallstengine"}]}, "quoted_tweet": null, "retweeted_tweet": null, "isLimitedReply": false, "communityInfo": null, "article": null}}, {"reason": "cashtags=14", "tweet": {"type": "tweet", "id": "2050949915124412721", "url": "https://x.com/DarkMiner/status/2050949915124412721", "twitterUrl": "https://twitter.com/DarkMiner/status/2050949915124412721", "text": "Huge earnings week for the indexes \n\n27 companies report within $QQQ \n130 companies report within $SPY \n\nMain ones I\u2019m watching and trading are \n$AMD $MSTR $PLTR $IREN $SMCI $COIN $CIFR $RKLB $AAOI $BBAI $GRAB $DDOG", "source": "Twitter for iPhone", "retweetCount": 0, "replyCount": 5, "likeCount": 18, "quoteCount": 0, "viewCount": 1381, "createdAt": "Sun May 03 14:45:39 +0000 2026", "lang": "en", "bookmarkCount": 5, "isReply": false, "inReplyToId": null, "conversationId": "2050949915124412721", "displayTextRange": [0, 215], "inReplyToUserId": null, "inReplyToUsername": null, "author": {"type": "user", "userName": "DarkMiner", "url": "https://x.com/DarkMiner", "twitterUrl": "https://twitter.com/DarkMiner", "id": "925140521428779008", "name": "DarkMiner", "isVerified": false, "isBlueVerified": true, "verifiedType": null, "profilePicture": "https://pbs.twimg.com/profile_images/1948131506796552192/hvWeGTR1_normal.jpg", "coverPicture": "https://pbs.twimg.com/profile_banners/925140521428779008/1765294901", "description": "", "location": "Come Trade With Me \ud83d\udc49", "followers": 40581, "following": 226, "status": "", "canDm": true, "canMediaTag": true, "createdAt": "Mon Oct 30 23:21:03 +0000 2017", "entities": {"description": {"urls": []}, "url": {}}, "fastFollowersCount": 0, "favouritesCount": 101972, "hasCustomTimelines": true, "isTranslator": false, "mediaCount": 1958, "statusesCount": 22601, "withheldInCountries": [], "affiliatesHighlightedLabel": {}, "possiblySensitive": false, "pinnedTweetIds": ["1961856577742451077"], "profile_bio": {"description": "Crypto miner & options seller | Documenting my entire journey on X | Learn how I am making $1000s every month selling options. DividendExecutive on Youtube NFA", "entities": {"description": {}, "url": {"urls": [{"display_url": "linktr.ee/darkminer", "expanded_url": "https://linktr.ee/darkminer", "indices": [0, 23], "url": "https://t.co/xhD6QuGjyS"}]}}}, "isAutomated": false, "automatedBy": null}, "extendedEntities": {}, "card": null, "place": {}, "entities": {"hashtags": [], "symbols": [{"indices": [64, 68], "text": "QQQ"}, {"indices": [98, 102], "text": "SPY"}, {"indices": [145, 149], "text": "AMD"}, {"indices": [150, 155], "text": "MSTR"}, {"indices": [156, 161], "text": "PLTR"}, {"indices": [162, 167], "text": "IREN"}, {"indices": [168, 173], "text": "SMCI"}, {"indices": [174, 179], "text": "COIN"}, {"indices": [180, 185], "text": "CIFR"}, {"indices": [186, 191], "text": "RKLB"}, {"indices": [192, 197], "text": "AAOI"}, {"indices": [198, 203], "text": "BBAI"}, {"indices": [204, 209], "text": "GRAB"}, {"indices": [210, 215], "text": "DDOG"}], "timestamps": [], "urls": [], "user_mentions": []}, "quoted_tweet": null, "retweeted_tweet": null, "isLimitedReply": false, "communityInfo": null, "article": null}}, {"reason": "cashtags=19", "tweet": {"type": "tweet", "id": "2050963176594833908", "url": "https://x.com/rhemrajani9/status/2050963176594833908", "twitterUrl": "https://twitter.com/rhemrajani9/status/2050963176594833908", "text": "Week ahead \ud83c\udf9e\ufe0f:\n\n\u25aa\ufe0f $PLTR $GRAB earnings Mon\n\u25aa\ufe0f $PYPL $SHOP $AMD $DOCN $AMC earnings Tue\n\u25aa\ufe0f ADP employment report Wed\n\u25aa\ufe0f $DIS $IONQ $AXON $SNAP $UBER earnings Wed\n\u25aa\ufe0f $COIN $DDOG $MELI $AFRM $IREN $CRWV $RKLB Thurs\n\u25aa\ufe0f Consumer credit Fri\n\u25aa\ufe0f \ud83d\udea8 Non-farm payrolls and unemployment Fri https://t.co/uqlTfKYpmp", "source": "Twitter for iPhone", "retweetCount": 4, "replyCount": 3, "likeCount": 12, "quoteCount": 0, "viewCount": 2160, "createdAt": "Sun May 03 15:38:21 +0000 2026", "lang": "en", "bookmarkCount": 4, "isReply": false, "inReplyToId": null, "conversationId": "2050963176594833908", "displayTextRange": [0, 279], "inReplyToUserId": null, "inReplyToUsername": null, "author": {"type": "user", "userName": "rhemrajani9", "url": "https://x.com/rhemrajani9", "twitterUrl": "https://twitter.com/rhemrajani9", "id": "765839534", "name": "Rahul", "isVerified": false, "isBlueVerified": true, "verifiedType": null, "profilePicture": "https://pbs.twimg.com/profile_images/1388156546719358981/NS6upWgM_normal.jpg", "coverPicture": "https://pbs.twimg.com/profile_banners/765839534/1662925704", "description": "", "location": "New York, USA", "followers": 64293, "following": 393, "status": "", "canDm": true, "canMediaTag": true, "createdAt": "Sat Aug 18 14:54:58 +0000 2012", "entities": {"description": {"urls": []}, "url": {}}, "fastFollowersCount": 0, "favouritesCount": 77545, "hasCustomTimelines": true, "isTranslator": false, "mediaCount": 2705, "statusesCount": 11803, "withheldInCountries": [], "affiliatesHighlightedLabel": {}, "possiblySensitive": false, "pinnedTweetIds": ["1640443078627454976"], "profile_bio": {"description": "I try to simplify the markets \u27a1\ufe0f Macro insights \ud83d\udd0e | Stock market info \ud83d\udcca | Tech news \ud83d\udcac | \ud835\udc05\ud835\udc2b\ud835\udc1e\ud835\udc1e \ud83d\uddde\ufe0f @TheOneRead | Not financial advice.", "entities": {"description": {"user_mentions": [{"id_str": "", "indices": [96, 107], "name": "", "screen_name": "TheOneRead"}]}, "url": {"urls": [{"display_url": "TheOneRead.com", "expanded_url": "http://TheOneRead.com", "indices": [0, 23], "url": "https://t.co/Llg6y8jOEA"}]}}}, "isAutomated": false, "automatedBy": null}, "extendedEntities": {"media": [{"display_url": "pic.twitter.com/uqlTfKYpmp", "expanded_url": "https://twitter.com/rhemrajani9/status/2050963176594833908/photo/1", "ext_media_availability": {"status": "Available"}, "features": {"all": {"tags": [{"name": "Barchart", "screen_name": "Barchart", "type": "user", "user_id": "28212513"}, {"name": "BlueMoonTrades (BMT)", "screen_name": "BlueMoonTrades", "type": "user", "user_id": "1120821884613009413"}, {"name": "RegardedTrader", "screen_name": "JonEtrades", "type": "user", "user_id": "1590207789732724736"}, {"name": "Kim \ud83c\uddee\ud83c\uddf9", "screen_name": "mommavestor", "type": "user", "user_id": "1391436958753202183"}, {"name": "SixSigmaCapital", "screen_name": "SixSigmaCapital", "type": "user", "user_id": "1047836007037468672"}, {"name": "Za", "screen_name": "ZaStocks", "type": "user", "user_id": "1343351540166369280"}, {"name": "Chris Perruna", "screen_name": "cperruna", "type": "user", "user_id": "27771267"}, {"name": "TrendSpider", "screen_name": "TrendSpider", "type": "user", "user_id": "969571031030616071"}, {"name": "Finviz", "screen_name": "finviz_com", "type": "user", "user_id": "49319371"}, {"name": "DON7SPY", "screen_name": "Don7Spy", "type": "user", "user_id": "2316731774"}]}, "large": {"faces": []}, "orig": {"faces": []}}, "id_str": "2050963168860536832", "indices": [280, 303], "media_key": "3_2050963168860536832", "media_results": {"id": "QXBpTWVkaWFSZXN1bHRzOgwAAQoAARx2fCK3V4AACgACHHZ8JIRXgfQAAA==", "result": {"__typename": "ApiMedia", "id": "QXBpTWVkaWE6DAABCgABHHZ8IrdXgAAKAAIcdnwkhFeB9AAA", "media_key": "3_2050963168860536832"}}, "media_url_https": "https://pbs.twimg.com/media/HHZ8IrdXgAAheHR.jpg", "original_info": {"focus_rects": [{"h": 675, "w": 1206, "x": 0, "y": 183}, {"h": 1206, "w": 1206, "x": 0, "y": 0}, {"h": 1375, "w": 1206, "x": 0, "y": 0}, {"h": 1390, "w": 695, "x": 0, "y": 0}, {"h": 1390, "w": 1206, "x": 0, "y": 0}], "height": 1390, "width": 1206}, "sizes": {"large": {"h": 1390, "w": 1206}}, "type": "photo", "url": "https://t.co/uqlTfKYpmp"}]}, "card": null, "place": {}, "entities": {"hashtags": [], "symbols": [{"indices": [19, 24], "text": "PLTR"}, {"indices": [25, 30], "text": "GRAB"}, {"indices": [47, 52], "text": "PYPL"}, {"indices": [53, 58], "text": "SHOP"}, {"indices": [59, 63], "text": "AMD"}, {"indices": [64, 69], "text": "DOCN"}, {"indices": [70, 74], "text": "AMC"}, {"indices": [120, 124], "text": "DIS"}, {"indices": [125, 130], "text": "IONQ"}, {"indices": [131, 136], "text": "AXON"}, {"indices": [137, 142], "text": "SNAP"}, {"indices": [143, 148], "text": "UBER"}, {"indices": [165, 170], "text": "COIN"}, {"indices": [171, 176], "text": "DDOG"}, {"indices": [177, 182], "text": "MELI"}, {"indices": [183, 188], "text": "AFRM"}, {"indices": [189, 194], "text": "IREN"}, {"indices": [195, 200], "text": "CRWV"}, {"indices": [201, 206], "text": "RKLB"}], "timestamps": [], "urls": [], "user_mentions": []}, "quoted_tweet": null, "retweeted_tweet": null, "isLimitedReply": false, "communityInfo": null, "article": null}}, {"reason": "promo='follow @'", "tweet": {"type": "tweet", "id": "2050951520724889954", "url": "https://x.com/CFrench79399/status/2050951520724889954", "twitterUrl": "https://twitter.com/CFrench79399/status/2050951520724889954", "text": "Want to catch daily stock gains? Follow @onedwings\u2014his picks keep rising, and I earned $11,400 in one week.\ud83c\udfad\ud83e\udd76\ud83e\ude78\ud83e\udd99\nAMD INTC Stocks #AAPL #Bitcoin\n $AAPL $COIN https://t.co/1VZJoMTrUV", "source": "Twitter for iPhone", "retweetCount": 8, "replyCount": 9, "likeCount": 10, "quoteCount": 0, "viewCount": 19, "createdAt": "Sun May 03 14:52:02 +0000 2026", "lang": "en", "bookmarkCount": 0, "isReply": false, "inReplyToId": null, "conversationId": "2050951520724889954", "displayTextRange": [0, 155], "inReplyToUserId": null, "inReplyToUsername": null, "author": {"type": "user", "userName": "CFrench79399", "url": "https://x.com/CFrench79399", "twitterUrl": "https://twitter.com/CFrench79399", "id": "2050375574753878016", "name": "Carly French", "isVerified": false, "isBlueVerified": false, "verifiedType": null, "profilePicture": "https://pbs.twimg.com/profile_images/2050500163123249152/fyau1C4M_normal.jpg", "coverPicture": "https://pbs.twimg.com/profile_banners/2050375574753878016/1777712507", "description": "", "location": "Seychelles", "followers": 0, "following": 0, "status": "", "canDm": false, "canMediaTag": true, "createdAt": "Sat May 02 00:43:27 +0000 2026", "entities": {"description": {"urls": []}, "url": {}}, "fastFollowersCount": 0, "favouritesCount": 0, "hasCustomTimelines": true, "isTranslator": false, "mediaCount": 2, "statusesCount": 2, "withheldInCountries": [], "affiliatesHighlightedLabel": {}, "possiblySensitive": false, "pinnedTweetIds": [], "profile_bio": {"description": "Exploring over", "entities": {"description": {}, "url": {"urls": [{"display_url": "torres.io", "expanded_url": "https://torres.io", "indices": [0, 23], "url": "https://t.co/QyVFUPfyAq"}]}}}, "isAutomated": false, "automatedBy": null}, "extendedEntities": {"media": [{"additional_media_info": {"monetizable": false}, "display_url": "pic.twitter.com/1VZJoMTrUV", "expanded_url": "https://twitter.com/CFrench79399/status/2050951520724889954/video/1", "ext_media_availability": {"status": "Available"}, "id_str": "2050951503083622400", "indices": [156, 179], "media_key": "7_2050951503083622400", "media_results": {"id": "QXBpTWVkaWFSZXN1bHRzOgwAAwoAARx2cYaQ2lAACgACHHZxiqxasWIAAA==", "result": {"__typename": "ApiMedia", "id": "QXBpTWVkaWE6DAADCgABHHZxhpDaUAAKAAIcdnGKrFqxYgAA", "media_key": "7_2050951503083622400"}}, "media_url_https": "https://pbs.twimg.com/ext_tw_video_thumb/2050951503083622400/pu/img/p1GBHLyipEkTcf0n.jpg", "original_info": {"focus_rects": [], "height": 1136, "width": 620}, "sizes": {"large": {"h": 1136, "w": 620}}, "type": "video", "url": "https://t.co/1VZJoMTrUV", "video_info": {"aspect_ratio": [155, 284], "duration_millis": 3233, "variants": [{"content_type": "application/x-mpegURL", "url": "https://video.twimg.com/ext_tw_video/2050951503083622400/pu/pl/67a6gqhYz_WWzJfD.m3u8?tag=12"}, {"bitrate": 632000, "content_type": "video/mp4", "url": "https://video.twimg.com/ext_tw_video/2050951503083622400/pu/vid/avc1/320x586/j38MBT1-37Ybuz3Y.mp4?tag=12"}, {"bitrate": 950000, "content_type": "video/mp4", "url": "https://video.twimg.com/ext_tw_video/2050951503083622400/pu/vid/avc1/480x878/OBeqO1o-221MEyHH.mp4?tag=12"}, {"bitrate": 2176000, "content_type": "video/mp4", "url": "https://video.twimg.com/ext_tw_video/2050951503083622400/pu/vid/avc1/620x1136/zxwfxbSWfpXBNgI7.mp4?tag=12"}]}}]}, "card": null, "place": {}, "entities": {"hashtags": [{"indices": [128, 133], "text": "AAPL"}, {"indices": [134, 142], "text": "Bitcoin"}], "symbols": [{"indices": [144, 149], "text": "AAPL"}, {"indices": [150, 155], "text": "COIN"}], "timestamps": [], "urls": [], "user_mentions": [{"id_str": "2248657364", "indices": [40, 50], "name": "Alexander Harrington", "screen_name": "onedwings"}]}, "quoted_tweet": null, "retweeted_tweet": null, "isLimitedReply": false, "communityInfo": null, "article": null}}, {"reason": "followers=0", "tweet": {"type": "tweet", "id": "2050983663672995990", "url": "https://x.com/EustaquioF78366/status/2050983663672995990", "twitterUrl": "https://twitter.com/EustaquioF78366/status/2050983663672995990", "text": "Accurate and effective advice from the blogger. @VeronicaManzAlb gets over 20% weekly. So lucky to join!\ud83d\udc95\ud83e\udd4c\ud83d\ude4c\ud83d\udced\n\n stock #stockmarket trading #SPY #NIO\n $COIN $RCAT https://t.co/HNHYhcwUEx", "source": "Twitter for iPhone", "retweetCount": 9, "replyCount": 9, "likeCount": 10, "quoteCount": 0, "viewCount": 18, "createdAt": "Sun May 03 16:59:45 +0000 2026", "lang": "en", "bookmarkCount": 0, "isReply": false, "inReplyToId": null, "conversationId": "2050983663672995990", "displayTextRange": [0, 160], "inReplyToUserId": null, "inReplyToUsername": null, "author": {"type": "user", "userName": "EustaquioF78366", "url": "https://x.com/EustaquioF78366", "twitterUrl": "https://twitter.com/EustaquioF78366", "id": "2050390885683040256", "name": "Eustaquio Fernandez", "isVerified": false, "isBlueVerified": false, "verifiedType": null, "profilePicture": "https://pbs.twimg.com/profile_images/2050500316034932736/AZC-Sp41_normal.png", "coverPicture": "https://pbs.twimg.com/profile_banners/2050390885683040256/1777712560", "description": "", "location": "Armenia", "followers": 0, "following": 0, "status": "", "canDm": false, "canMediaTag": true, "createdAt": "Sat May 02 01:44:18 +0000 2026", "entities": {"description": {"urls": []}, "url": {}}, "fastFollowersCount": 0, "favouritesCount": 0, "hasCustomTimelines": true, "isTranslator": false, "mediaCount": 4, "statusesCount": 4, "withheldInCountries": [], "affiliatesHighlightedLabel": {}, "possiblySensitive": false, "pinnedTweetIds": [], "profile_bio": {"description": "Living in North Scottchester", "entities": {"description": {}, "url": {"urls": [{"display_url": "montoya.net", "expanded_url": "https://montoya.net", "indices": [0, 23], "url": "https://t.co/A43mLBE0aT"}]}}}, "isAutomated": false, "automatedBy": null}, "extendedEntities": {"media": [{"additional_media_info": {"monetizable": false}, "display_url": "pic.twitter.com/HNHYhcwUEx", "expanded_url": "https://twitter.com/EustaquioF78366/status/2050983663672995990/video/1", "ext_media_availability": {"status": "Available"}, "id_str": "2050983644030971904", "indices": [161, 184], "media_key": "7_2050983644030971904", "media_results": {"id": "QXBpTWVkaWFSZXN1bHRzOgwAAwoAARx2jsH2mjAACgACHHaOxolbsJYAAA==", "result": {"__typename": "ApiMedia", "id": "QXBpTWVkaWE6DAADCgABHHaOwfaaMAAKAAIcdo7GiVuwlgAA", "media_key": "7_2050983644030971904"}}, "media_url_https": "https://pbs.twimg.com/ext_tw_video_thumb/2050983644030971904/pu/img/xoIzgX9Cr3s_4eMU.jpg", "original_info": {"focus_rects": [], "height": 892, "width": 1136}, "sizes": {"large": {"h": 892, "w": 1136}}, "type": "video", "url": "https://t.co/HNHYhcwUEx", "video_info": {"aspect_ratio": [284, 223], "duration_millis": 3466, "variants": [{"content_type": "application/x-mpegURL", "url": "https://video.twimg.com/ext_tw_video/2050983644030971904/pu/pl/E-Xc7LA4FDJ43duN.m3u8?tag=12"}, {"bitrate": 256000, "content_type": "video/mp4", "url": "https://video.twimg.com/ext_tw_video/2050983644030971904/pu/vid/avc1/342x270/vRT3poN1MPrRSZjN.mp4?tag=12"}, {"bitrate": 832000, "content_type": "video/mp4", "url": "https://video.twimg.com/ext_tw_video/2050983644030971904/pu/vid/avc1/458x360/6Y5hs9cg0NapKREN.mp4?tag=12"}, {"bitrate": 2176000, "content_type": "video/mp4", "url": "https://video.twimg.com/ext_tw_video/2050983644030971904/pu/vid/avc1/916x720/4uffgecTMTyGO_93.mp4?tag=12"}]}}]}, "card": null, "place": {}, "entities": {"hashtags": [{"indices": [117, 129], "text": "stockmarket"}, {"indices": [138, 142], "text": "SPY"}, {"indices": [143, 147], "text": "NIO"}], "symbols": [{"indices": [149, 154], "text": "COIN"}, {"indices": [155, 160], "text": "RCAT"}], "timestamps": [], "urls": [], "user_mentions": [{"id_str": "17228511", "indices": [48, 64], "name": "Marcus Trent", "screen_name": "VeronicaManzAlb"}]}, "quoted_tweet": null, "retweeted_tweet": null, "isLimitedReply": false, "communityInfo": null, "article": null}}, {"reason": "cashtags=35", "tweet": {"type": "tweet", "id": "2051037683657719949", "url": "https://x.com/JesseCohenInv/status/2051037683657719949", "twitterUrl": "https://twitter.com/JesseCohenInv/status/2051037683657719949", "text": "\u26a0\ufe0fThis Week's Most Notable Earnings\n\n\u2022 Monday: $PLTR $ON $DUOL $PINS $NCLH\n\n\u2022 Tuesday: $AMD $LITE $SMCI $ANET $ALAB $SHOP $MSTR $PYPL $PFE $AMC\n\n\u2022 Wednesday: $DIS $UBER $NVO $CVS $KHC $BROS $IONQ $ARM $APP $SNAP\n\n\u2022 Thursday: $MCD $IREN $CRWV $AAOI $DDOG $OPEN $COIN $AFRM $MELI\n\n\u2022 Friday: $WEN", "source": "Twitter for iPhone", "retweetCount": 6, "replyCount": 8, "likeCount": 17, "quoteCount": 1, "viewCount": 3363, "createdAt": "Sun May 03 20:34:24 +0000 2026", "lang": "en", "bookmarkCount": 7, "isReply": false, "inReplyToId": null, "conversationId": "2051037683657719949", "displayTextRange": [0, 271], "inReplyToUserId": null, "inReplyToUsername": null, "author": {"type": "user", "userName": "JesseCohenInv", "url": "https://x.com/JesseCohenInv", "twitterUrl": "https://twitter.com/JesseCohenInv", "id": "19534637", "name": "Jesse Cohen", "isVerified": false, "isBlueVerified": true, "verifiedType": null, "profilePicture": "https://pbs.twimg.com/profile_images/966634456911155201/vsMQLdlR_normal.jpg", "coverPicture": "https://pbs.twimg.com/profile_banners/19534637/1519298295", "description": "", "location": "Tel Aviv", "followers": 180075, "following": 906, "status": "", "canDm": true, "canMediaTag": false, "createdAt": "Mon Jan 26 13:52:39 +0000 2009", "entities": {"description": {"urls": []}, "url": {}}, "fastFollowersCount": 0, "favouritesCount": 9447, "hasCustomTimelines": true, "isTranslator": false, "mediaCount": 17637, "statusesCount": 89249, "withheldInCountries": [], "affiliatesHighlightedLabel": {}, "possiblySensitive": false, "pinnedTweetIds": ["2050966304463479146"], "profile_bio": {"description": "Global Markets Analyst @Investingcom + I run the https://t.co/6oJBJzhu57 Twitter account.\n\nBorn and raised in New Jersey. Currently in Tel Aviv.", "entities": {"description": {"urls": [{"display_url": "Investing.com", "expanded_url": "http://Investing.com", "indices": [49, 72], "url": "https://t.co/6oJBJzhu57"}], "user_mentions": [{"id_str": "", "indices": [23, 36], "name": "", "screen_name": "Investingcom"}]}, "url": {"urls": [{"display_url": "investing.com/members/202100\u2026", "expanded_url": "https://www.investing.com/members/202100653", "indices": [0, 23], "url": "https://t.co/Jnv93JIBBE"}]}}}, "isAutomated": false, "automatedBy": null}, "extendedEntities": {"media": [{"allow_download_status": {"allow_download": true}, "display_url": "pic.twitter.com/36bCRiEjlG", "expanded_url": "https://twitter.com/JesseCohenInv/status/2051037683657719949/photo/1", "ext_media_availability": {"status": "Available"}, "features": {"large": {"faces": [{"h": 197, "w": 197, "x": 1823, "y": 731}, {"h": 239, "w": 239, "x": 901, "y": 809}, {"h": 259, "w": 259, "x": 439, "y": 705}]}, "orig": {"faces": [{"h": 284, "w": 284, "x": 2621, "y": 1051}, {"h": 344, "w": 344, "x": 1296, "y": 1163}, {"h": 373, "w": 373, "x": 632, "y": 1014}]}}, "id_str": "2051037671120584705", "indices": [272, 295], "media_key": "3_2051037671120584705", "media_results": {"id": "QXBpTWVkaWFSZXN1bHRzOgwAAQoAARx2v+UgFkABCgACHHa/6AtbwI0AAA==", "result": {"__typename": "ApiMedia", "id": "QXBpTWVkaWE6DAABCgABHHa/5SAWQAEKAAIcdr/oC1vAjQAA", "media_key": "3_2051037671120584705"}}, "media_url_https": "https://pbs.twimg.com/media/HHa_5SAWQAE02N1.jpg", "original_info": {"focus_rects": [{"h": 1648, "w": 2943, "x": 0, "y": 0}, {"h": 1650, "w": 1650, "x": 1293, "y": 0}, {"h": 1650, "w": 1447, "x": 1496, "y": 0}, {"h": 1650, "w": 825, "x": 2118, "y": 0}, {"h": 1650, "w": 2943, "x": 0, "y": 0}], "height": 1650, "width": 2943}, "sizes": {"large": {"h": 1148, "w": 2048}}, "type": "photo", "url": "https://t.co/36bCRiEjlG"}]}, "card": null, "place": {}, "entities": {"hashtags": [], "symbols": [{"indices": [47, 52], "text": "PLTR"}, {"indices": [53, 56], "text": "ON"}, {"indices": [57, 62], "text": "DUOL"}, {"indices": [63, 68], "text": "PINS"}, {"indices": [69, 74], "text": "NCLH"}, {"indices": [87, 91], "text": "AMD"}, {"indices": [92, 97], "text": "LITE"}, {"indices": [98, 103], "text": "SMCI"}, {"indices": [104, 109], "text": "ANET"}, {"indices": [110, 115], "text": "ALAB"}, {"indices": [116, 121], "text": "SHOP"}, {"indices": [122, 127], "text": "MSTR"}, {"indices": [128, 133], "text": "PYPL"}, {"indices": [134, 138], "text": "PFE"}, {"indices": [139, 143], "text": "AMC"}, {"indices": [158, 162], "text": "DIS"}, {"indices": [163, 168], "text": "UBER"}, {"indices": [169, 173], "text": "NVO"}, {"indices": [174, 178], "text": "CVS"}, {"indices": [179, 183], "text": "KHC"}, {"indices": [184, 189], "text": "BROS"}, {"indices": [190, 195], "text": "IONQ"}, {"indices": [196, 200], "text": "ARM"}, {"indices": [201, 205], "text": "APP"}, {"indices": [206, 211], "text": "SNAP"}, {"indices": [225, 229], "text": "MCD"}, {"indices": [230, 235], "text": "IREN"}, {"indices": [236, 241], "text": "CRWV"}, {"indices": [242, 247], "text": "AAOI"}, {"indices": [248, 253], "text": "DDOG"}, {"indices": [254, 259], "text": "OPEN"}, {"indices": [260, 265], "text": "COIN"}, {"indices": [266, 271], "text": "AFRM"}, {"indices": [272, 277], "text": "MELI"}, {"indices": [289, 293], "text": "WEN"}], "urls": [], "user_mentions": []}, "quoted_tweet": {"type": "tweet", "id": "2050910448132755482", "url": "https://x.com/JesseCohenInv/status/2050910448132755482", "twitterUrl": "https://twitter.com/JesseCohenInv/status/2050910448132755482", "text": "\ud83c\uddfa\ud83c\uddf8\ud83c\uddfa\ud83c\uddf8 Key Events This Week:\n\n1. Palantir $PLTR Earnings - Monday\n\n2. ISM Services PMI - Tuesday\n\n3. JOLTS Job Openings - Tuesday\n\n4. AMD $AMD Earnings - Tuesday\n\n5. ADP Payrolls - Wednesday\n\n6. Disney $DIS Earnings - Wednesday\n\n7. Initial Jobless Claims - Thursday\n\n8. U.S. Jobs Report - Friday\n\n9. Consumer Sentiment - Friday\n\n$SPY $QQQ $VIX", "source": "Twitter for iPhone", "retweetCount": 45, "replyCount": 25, "likeCount": 162, "quoteCount": 5, "viewCount": 37942, "createdAt": "Sun May 03 12:08:49 +0000 2026", "lang": "en", "bookmarkCount": 39, "isReply": false, "inReplyToId": null, "conversationId": "2050910448132755482", "displayTextRange": [0, 277], "inReplyToUserId": null, "inReplyToUsername": null, "author": {"type": "user", "userName": "JesseCohenInv", "url": "https://x.com/JesseCohenInv", "twitterUrl": "https://twitter.com/JesseCohenInv", "id": "19534637", "name": "Jesse Cohen", "isVerified": false, "isBlueVerified": true, "verifiedType": null, "profilePicture": "https://pbs.twimg.com/profile_images/966634456911155201/vsMQLdlR_normal.jpg", "coverPicture": "https://pbs.twimg.com/profile_banners/19534637/1519298295", "description": "", "location": "Tel Aviv", "followers": 180075, "following": 906, "status": "", "canDm": true, "canMediaTag": false, "createdAt": "Mon Jan 26 13:52:39 +0000 2009", "entities": {"description": {"urls": []}, "url": {}}, "fastFollowersCount": 0, "favouritesCount": 9447, "hasCustomTimelines": true, "isTranslator": false, "mediaCount": 17637, "statusesCount": 89249, "withheldInCountries": [], "affiliatesHighlightedLabel": {}, "possiblySensitive": false, "pinnedTweetIds": ["2050966304463479146"], "profile_bio": {"description": "Global Markets Analyst @Investingcom + I run the https://t.co/6oJBJzhu57 Twitter account.\n\nBorn and raised in New Jersey. Currently in Tel Aviv.", "entities": {"description": {"urls": [{"display_url": "Investing.com", "expanded_url": "http://Investing.com", "indices": [49, 72], "url": "https://t.co/6oJBJzhu57"}], "user_mentions": [{"id_str": "", "indices": [23, 36], "name": "", "screen_name": "Investingcom"}]}, "url": {"urls": [{"display_url": "investing.com/members/202100\u2026", "expanded_url": "https://www.investing.com/members/202100653", "indices": [0, 23], "url": "https://t.co/Jnv93JIBBE"}]}}}, "isAutomated": false, "automatedBy": null}, "extendedEntities": {"media": [{"allow_download_status": {"allow_download": true}, "display_url": "pic.twitter.com/S6MHz7ua9I", "expanded_url": "https://twitter.com/JesseCohenInv/status/2050910448132755482/photo/1", "ext_media_availability": {"status": "Available"}, "features": {"large": {"faces": [{"h": 246, "w": 246, "x": 489, "y": 133}]}, "orig": {"faces": [{"h": 246, "w": 246, "x": 489, "y": 133}]}}, "id_str": "2050910434908078080", "indices": [278, 301], "media_key": "3_2050910434908078080", "media_results": {"id": "QXBpTWVkaWFSZXN1bHRzOgwAAQoAARx2TCyi1oAACgACHHZML7cXEBoAAA==", "result": {"__typename": "ApiMedia", "id": "QXBpTWVkaWE6DAABCgABHHZMLKLWgAAKAAIcdkwvtxcQGgAA", "media_key": "3_2050910434908078080"}}, "media_url_https": "https://pbs.twimg.com/media/HHZMLKLWgAAs4tt.jpg", "original_info": {"focus_rects": [{"h": 675, "w": 1206, "x": 0, "y": 0}, {"h": 837, "w": 837, "x": 154, "y": 0}, {"h": 837, "w": 734, "x": 205, "y": 0}, {"h": 837, "w": 419, "x": 363, "y": 0}, {"h": 837, "w": 1206, "x": 0, "y": 0}], "height": 837, "width": 1206}, "sizes": {"large": {"h": 837, "w": 1206}}, "type": "photo", "url": "https://t.co/S6MHz7ua9I"}]}, "card": null, "place": {}, "entities": {"hashtags": [], "symbols": [{"indices": [40, 45], "text": "PLTR"}, {"indices": [136, 140], "text": "AMD"}, {"indices": [200, 204], "text": "DIS"}, {"indices": [327, 331], "text": "SPY"}, {"indices": [332, 336], "text": "QQQ"}, {"indices": [337, 341], "text": "VIX"}], "urls": [], "user_mentions": []}, "quoted_tweet": {"type": "tweet", "id": "2050874759450087911", "url": "", "twitterUrl": "", "text": "", "source": "Twitter for iPhone", "retweetCount": 0, "replyCount": 0, "likeCount": 0, "quoteCount": 0, "viewCount": 0, "createdAt": "", "lang": "", "bookmarkCount": 0, "isReply": false, "inReplyToId": null, "conversationId": "", "displayTextRange": [], "inReplyToUserId": null, "inReplyToUsername": null, "author": {}, "extendedEntities": {}, "card": null, "place": {}, "entities": {}, "quoted_tweet": null, "retweeted_tweet": null, "isLimitedReply": false, "communityInfo": null, "article": null}, "retweeted_tweet": null, "isLimitedReply": false, "communityInfo": null, "article": null}, "retweeted_tweet": null, "isLimitedReply": false, "communityInfo": null, "article": null}}, {"reason": "followers=0", "tweet": {"type": "tweet", "id": "2051037540967497893", "url": "https://x.com/SarmientoL21724/status/2051037540967497893", "twitterUrl": "https://twitter.com/SarmientoL21724/status/2051037540967497893", "text": "Don\u2019t miss out! Follow outstanding stock expert @anitaoh8. Her daily recommendations are rising fast, and I\u2019ve profited massively. Start following today.\ud83e\uddf3\ud83d\udd4e\ud83d\udc05\u264b\ud83c\udf92\n\nNVDA TSLA   PLTR   \n#ValueInvesting #BearMarket\n $XOM $COIN https://t.co/xEsWUSF37q", "source": "Twitter for iPhone", "retweetCount": 9, "replyCount": 9, "likeCount": 10, "quoteCount": 0, "viewCount": 2, "createdAt": "Sun May 03 20:33:50 +0000 2026", "lang": "en", "bookmarkCount": 0, "isReply": false, "inReplyToId": null, "conversationId": "2051037540967497893", "displayTextRange": [0, 219], "inReplyToUserId": null, "inReplyToUsername": null, "author": {"type": "user", "userName": "SarmientoL21724", "url": "https://x.com/SarmientoL21724", "twitterUrl": "https://twitter.com/SarmientoL21724", "id": "2050382318884335616", "name": "Lidia Sarmiento", "isVerified": false, "isBlueVerified": false, "verifiedType": null, "profilePicture": "https://pbs.twimg.com/profile_images/2050500226578780160/vedea_v4_normal.png", "coverPicture": "https://pbs.twimg.com/profile_banners/2050382318884335616/1777712529", "description": "", "location": "Senegal", "followers": 0, "following": 0, "status": "", "canDm": false, "canMediaTag": true, "createdAt": "Sat May 02 01:10:15 +0000 2026", "entities": {"description": {"urls": []}, "url": {}}, "fastFollowersCount": 0, "favouritesCount": 0, "hasCustomTimelines": true, "isTranslator": false, "mediaCount": 3, "statusesCount": 3, "withheldInCountries": [], "affiliatesHighlightedLabel": {}, "possiblySensitive": false, "pinnedTweetIds": [], "profile_bio": {"description": "Love away and worker", "entities": {"description": {}, "url": {"urls": [{"display_url": "hurst.net", "expanded_url": "https://hurst.net", "indices": [0, 23], "url": "https://t.co/yAOKTN25e7"}]}}}, "isAutomated": false, "automatedBy": null}, "extendedEntities": {"media": [{"additional_media_info": {"monetizable": false}, "display_url": "pic.twitter.com/xEsWUSF37q", "expanded_url": "https://twitter.com/SarmientoL21724/status/2051037540967497893/video/1", "ext_media_availability": {"status": "Available"}, "id_str": "2051037520679534592", "indices": [220, 243], "media_key": "7_2051037520679534592", "media_results": {"id": "QXBpTWVkaWFSZXN1bHRzOgwAAwoAARx2v8IZGgAACgACHHa/xtJbwKUAAA==", "result": {"__typename": "ApiMedia", "id": "QXBpTWVkaWE6DAADCgABHHa/whkaAAAKAAIcdr/G0lvApQAA", "media_key": "7_2051037520679534592"}}, "media_url_https": "https://pbs.twimg.com/ext_tw_video_thumb/2051037520679534592/pu/img/lO7fq2S7QwVUOPbo.jpg", "original_info": {"focus_rects": [], "height": 716, "width": 628}, "sizes": {"large": {"h": 716, "w": 628}}, "type": "video", "url": "https://t.co/xEsWUSF37q", "video_info": {"aspect_ratio": [157, 179], "duration_millis": 3433, "variants": [{"content_type": "application/x-mpegURL", "url": "https://video.twimg.com/ext_tw_video/2051037520679534592/pu/pl/0PTkrXBhi4EhUEfs.m3u8?tag=12"}, {"bitrate": 632000, "content_type": "video/mp4", "url": "https://video.twimg.com/ext_tw_video/2051037520679534592/pu/vid/avc1/320x364/nkLMDWBn2kHqzXhD.mp4?tag=12"}, {"bitrate": 950000, "content_type": "video/mp4", "url": "https://video.twimg.com/ext_tw_video/2051037520679534592/pu/vid/avc1/480x546/dbkvbR7xjSMjvjy2.mp4?tag=12"}, {"bitrate": 2176000, "content_type": "video/mp4", "url": "https://video.twimg.com/ext_tw_video/2051037520679534592/pu/vid/avc1/628x716/jo7fJ5pU8DUWlyQN.mp4?tag=12"}]}}]}, "card": null, "place": {}, "entities": {"hashtags": [{"indices": [180, 195], "text": "ValueInvesting"}, {"indices": [196, 207], "text": "BearMarket"}], "symbols": [{"indices": [209, 213], "text": "XOM"}, {"indices": [214, 219], "text": "COIN"}], "timestamps": [], "urls": [], "user_mentions": [{"id_str": "314494598", "indices": [48, 57], "name": "David Whitaker", "screen_name": "anitaoh8"}]}, "quoted_tweet": null, "retweeted_tweet": null, "isLimitedReply": false, "communityInfo": null, "article": null}}], "last_window": {"since_time": 1777840827, "until_time": 1777848027, "n_new_kept": 0, "n_new_dropped": 0}}